{
  "nodes": [
    {
      "x": 78564,
      "y": 106167,
      "id": "270509765",
      "fame": 0.2,
      "type": "MultiConnection"
    },
    {
      "x": 72508,
      "y": 72643,
      "id": "270509772",
      "fame": 0.2,
      "type": "MultiConnection"
    },
    {
      "x": 134331,
      "y": 14021,
      "id": "270509781",
      "fame": 0.2,
      "type": "MultiConnection"
    },
    {
      "x": 118669,
      "y": 9784,
      "id": "270509783",
      "fame": 0.2,
      "type": "MultiConnection"
    },
    {
      "x": 204670,
      "y": 108251,
      "id": "276019110",
      "fame": 0.2,
      "type": "MultiConnection"
    },
    {
      "x": 186774,
      "y": 101678,
      "id": "276019111",
      "fame": 0.2,
      "type": "MultiConnection"
    },
    {
      "x": 180355,
      "y": 97393,
      "id": "276019112",
      "fame": 0.2,
      "type": "MultiConnection"
    },
    {
      "x": 175925,
      "y": 95454,
      "id": "276019113",
      "fame": 0.2,
      "type": "MultiConnection"
    },
    {
      "x": 168906,
      "y": 92262,
      "id": "276019114",
      "fame": 0.2,
      "type": "MultiConnection"
    },
    {
      "x": 162485,
      "y": 90227,
      "id": "276019116",
      "fame": 0.2,
      "type": "MultiConnection"
    },
    {
      "x": 158069,
      "y": 88976,
      "id": "276019117",
      "fame": 0.2,
      "type": "MultiConnection"
    },
    {
      "x": 150911,
      "y": 88813,
      "id": "276019118",
      "fame": 0.2,
      "type": "MultiConnection"
    },
    {
      "x": 148700,
      "y": 87962,
      "id": "276019120",
      "fame": 0.2,
      "type": "MultiConnection"
    },
    {
      "x": 147337,
      "y": 87326,
      "id": "276019121",
      "fame": 0.2,
      "type": "MultiConnection"
    },
    {
      "x": 142154,
      "y": 83165,
      "id": "276019122",
      "fame": 0.2,
      "type": "MultiConnection"
    },
    {
      "x": 141392,
      "y": 82780,
      "id": "276019123",
      "fame": 0.2,
      "type": "MultiConnection"
    },
    {
      "x": 134327,
      "y": 82160,
      "id": "276019125",
      "fame": 0.2,
      "type": "MultiConnection"
    },
    {
      "x": 122574,
      "y": 82388,
      "id": "276019127",
      "fame": 0.2,
      "type": "MultiConnection"
    },
    {
      "x": 119858,
      "y": 82366,
      "id": "276019128",
      "fame": 0.2,
      "type": "MultiConnection"
    },
    {
      "x": 115622,
      "y": 82917,
      "id": "276019129",
      "fame": 0.2,
      "type": "MultiConnection"
    },
    {
      "x": 109598,
      "y": 84185,
      "id": "276019130",
      "fame": 0.2,
      "type": "MultiConnection"
    },
    {
      "x": 104264,
      "y": 85172,
      "id": "276019131",
      "fame": 0.2,
      "type": "MultiConnection"
    },
    {
      "x": 102982,
      "y": 81887,
      "id": "276019132",
      "fame": 0.2,
      "type": "MultiConnection"
    },
    {
      "x": 101221,
      "y": 79234,
      "id": "276019133",
      "fame": 0.2,
      "type": "MultiConnection"
    },
    {
      "x": 99069,
      "y": 77048,
      "id": "276019135",
      "fame": 0.2,
      "type": "MultiConnection"
    },
    {
      "x": 96176,
      "y": 75942,
      "id": "276019137",
      "fame": 0.2,
      "type": "MultiConnection"
    },
    {
      "x": 90549,
      "y": 75032,
      "id": "276019138",
      "fame": 0.2,
      "type": "MultiConnection"
    },
    {
      "x": 85284,
      "y": 74625,
      "id": "276019140",
      "fame": 0.2,
      "type": "MultiConnection"
    },
    {
      "x": 208001,
      "y": 110084,
      "id": "276019163",
      "fame": 0.2,
      "type": "MultiConnection"
    },
    {
      "x": 0,
      "y": 54106,
      "id": "280326655",
      "fame": 0.2,
      "type": "MultiConnection"
    },
    {
      "x": 45229,
      "y": 41932,
      "id": "280327075",
      "fame": 0.2,
      "type": "MultiConnection"
    },
    {
      "x": 45990,
      "y": 65965,
      "id": "280327081",
      "fame": 0.2,
      "type": "MultiConnection"
    },
    {
      "x": 35916,
      "y": 80753,
      "id": "280327098",
      "fame": 0.2,
      "type": "MultiConnection"
    },
    {
      "x": 53145,
      "y": 36341,
      "id": "281997433",
      "fame": 0.2,
      "type": "MultiConnection"
    },
    {
      "x": 54237,
      "y": 27851,
      "id": "281997435",
      "fame": 0.2,
      "type": "MultiConnection"
    },
    {
      "x": 54639,
      "y": 25353,
      "id": "281997436",
      "fame": 0.2,
      "type": "MultiConnection"
    },
    {
      "x": 60107,
      "y": 17272,
      "id": "281997438",
      "fame": 0.2,
      "type": "MultiConnection"
    },
    {
      "x": 72245,
      "y": 8968,
      "id": "281997440",
      "fame": 0.2,
      "type": "MultiConnection"
    },
    {
      "x": 86272,
      "y": 1932,
      "id": "281997445",
      "fame": 0.2,
      "type": "MultiConnection"
    },
    {
      "x": 96478,
      "y": 489,
      "id": "281997447",
      "fame": 0.2,
      "type": "MultiConnection"
    },
    {
      "x": 102951,
      "y": 3776,
      "id": "281997448",
      "fame": 0.2,
      "type": "MultiConnection"
    },
    {
      "x": 54483,
      "y": 41109,
      "id": "281997982",
      "fame": 0.2,
      "type": "MultiConnection"
    },
    {
      "x": 52700,
      "y": 33142,
      "id": "281997984",
      "fame": 0.2,
      "type": "MultiConnection"
    },
    {
      "x": 55326,
      "y": 23251,
      "id": "281997985",
      "fame": 0.2,
      "type": "MultiConnection"
    },
    {
      "x": 70349,
      "y": 9697,
      "id": "281997986",
      "fame": 0.2,
      "type": "MultiConnection"
    },
    {
      "x": 81679,
      "y": 5904,
      "id": "281997988",
      "fame": 0.2,
      "type": "MultiConnection"
    },
    {
      "x": 82466,
      "y": 5548,
      "id": "281997989",
      "fame": 0.2,
      "type": "MultiConnection"
    },
    {
      "x": 94100,
      "y": 0,
      "id": "281997991",
      "fame": 0.2,
      "type": "MultiConnection"
    },
    {
      "x": 106997,
      "y": 6811,
      "id": "281997992",
      "fame": 0.2,
      "type": "MultiConnection"
    },
    {
      "x": 75058,
      "y": 68575,
      "id": "281998256",
      "fame": 0.2,
      "type": "MultiConnection"
    }
  ]
}